section.py
section_run.py
section_explore-1.1.2.dist-info/METADATA
section_explore-1.1.2.dist-info/WHEEL
section_explore-1.1.2.dist-info/entry_points.txt
section_explore-1.1.2.dist-info/top_level.txt
section_explore-1.1.2.dist-info/RECORD
