Metadata-Version: 2.1
Name: section-explore
Version: 1.1.2
Summary: Read a text/config file by sections
Home-page: https://github.com/theglossy1/section
Author: theglossy1
Author-email: develop@jemnetworks.com
License: License :: OSI Approved :: MIT License
Platform: UNKNOWN
Requires-Dist: more-argparse
